hypertune/__init__.py
hypertune/iteration_lineage.py
hypertune/logger.py
hypertune/pkg.py
hypertune/matrix/__init__.py
hypertune/matrix/dist.py
hypertune/matrix/hyperopt.py
hypertune/matrix/utils.py
hypertune/search_managers/__init__.py
hypertune/search_managers/base.py
hypertune/search_managers/spec.py
hypertune/search_managers/utils.py
hypertune/search_managers/bayesian_optimization/__init__.py
hypertune/search_managers/bayesian_optimization/acquisition_function.py
hypertune/search_managers/bayesian_optimization/manager.py
hypertune/search_managers/bayesian_optimization/optimizer.py
hypertune/search_managers/bayesian_optimization/space.py
hypertune/search_managers/grid_search/__init__.py
hypertune/search_managers/grid_search/manager.py
hypertune/search_managers/hyperband/__init__.py
hypertune/search_managers/hyperband/manager.py
hypertune/search_managers/hyperopt/__init__.py
hypertune/search_managers/hyperopt/manager.py
hypertune/search_managers/mapping/__init__.py
hypertune/search_managers/mapping/manager.py
hypertune/search_managers/random_search/__init__.py
hypertune/search_managers/random_search/manager.py
hypertune-1.2.1.dist-info/LICENSE
hypertune-1.2.1.dist-info/METADATA
hypertune-1.2.1.dist-info/WHEEL
hypertune-1.2.1.dist-info/top_level.txt
hypertune-1.2.1.dist-info/RECORD
