Metadata-Version: 2.1
Name: hypertune
Version: 1.2.1
Summary: A library for performing hyperparameter optimization with Polyaxon.
Home-page: https://github.com/polyaxon/hypertune
Author: Polyaxon, Inc.
Author-email: contact@polyaxon.com
Maintainer: Polyaxon, Inc.
Maintainer-email: contact@polyaxon.com
License: Apache 2.0
Keywords: polyaxon,aws,s3,microsoft,azure,google cloud storage,gcs,deep-learning,machine-learning,data-science,neural-networks,artificial-intelligence,ai,reinforcement-learning,kubernetes,aws,microsoft,azure,google cloud,tensorFlow,pytorch,matplotlib,plotly,visualization,analytics,hyperopt,scikit-learn,optimization,bayesian-optimization
Platform: any
Classifier: Intended Audience :: Information Technology
Classifier: Intended Audience :: System Administrators
Classifier: Intended Audience :: Developers
Classifier: Intended Audience :: Science/Research
Classifier: Operating System :: OS Independent
Classifier: Programming Language :: Python :: 3
Classifier: Programming Language :: Python
Classifier: Topic :: Software Development :: Libraries :: Application Frameworks
Classifier: Topic :: Software Development :: Libraries :: Python Modules
Classifier: Topic :: Software Development :: Libraries
Classifier: Topic :: Software Development
Classifier: Topic :: Scientific/Engineering :: Artificial Intelligence
Classifier: Typing :: Typed
Classifier: Programming Language :: Python :: 3 :: Only
Classifier: Programming Language :: Python :: 3.6
Classifier: Programming Language :: Python :: 3.7
Classifier: Programming Language :: Python :: 3.8
Classifier: Programming Language :: Python :: 3.9
Classifier: Programming Language :: Python :: 3.10
Classifier: Programming Language :: Python :: 3.11
Requires-Python: >=3.8
License-File: LICENSE
Provides-Extra: all
Requires-Dist: scikit-learn; extra == "all"
Requires-Dist: hyperopt; extra == "all"
Provides-Extra: dev
Requires-Dist: pandas; extra == "dev"
Requires-Dist: ipython; extra == "dev"
Requires-Dist: numpy; extra == "dev"
Requires-Dist: scipy; extra == "dev"
Requires-Dist: scikit-learn<1.6; extra == "dev"
Requires-Dist: hyperopt<0.2.8; extra == "dev"
Requires-Dist: setuptools; extra == "dev"
Provides-Extra: polyaxon
Requires-Dist: polyaxon; extra == "polyaxon"
